LICENSE
README.md
setup.cfg
setup.py
pydtc/__init__.py
pydtc/connection.py
pydtc/formauth.py
pydtc/parallelize.py
pydtc/pydtc.py
pydtc/utils.py
pydtc.egg-info/PKG-INFO
pydtc.egg-info/SOURCES.txt
pydtc.egg-info/dependency_links.txt
pydtc.egg-info/requires.txt
pydtc.egg-info/top_level.txt