Metadata-Version: 2.1
Name: pydtc
Version: 0.4.1
Summary: tools collection for data engineer
Home-page: https://github.com/cctester/pydtc
Author: cctester
Author-email: cctester2001@gmail.com
License: UNKNOWN
Keywords: pandas,multiprocessing,database,restapi,requests
Platform: UNKNOWN
Classifier: Development Status :: 3 - Alpha
Classifier: Intended Audience :: Developers
Classifier: Topic :: Software Development :: Build Tools
Classifier: License :: OSI Approved :: BSD License
Classifier: Programming Language :: Python :: 3
Requires-Python: >=3.5
License-File: LICENSE
